setup.cfg
setup.py
bin/dlbot
dlbot.egg-info/PKG-INFO
dlbot.egg-info/SOURCES.txt
dlbot.egg-info/dependency_links.txt
dlbot.egg-info/requires.txt
dlbot.egg-info/top_level.txt
limbo/__init__.py
limbo/fakeserver.py
limbo/limbo.py
limbo/server.py
limbo/plugins/__init__.py
limbo/plugins/get.py
limbo/plugins/help.py
test/test.py
test/test_cmd.py