Metadata-Version: 1.1
Name: dlbot
Version: 0.0.4
Summary: Simple and Clean Slack Chatbot
Home-page: https://github.com/dataloop/dlbot
Author: Dataloop
Author-email: info@dataloop.io
License: MIT
Platform: UNKNOWN
Classifier: Development Status :: 4 - Beta
Classifier: Intended Audience :: Developers
Classifier: Natural Language :: English
Classifier: License :: OSI Approved :: MIT License
Classifier: Programming Language :: Python
Classifier: Programming Language :: Python :: 2.6
Classifier: Programming Language :: Python :: 2.7
Classifier: Programming Language :: Python :: 3.4
